py4macro/__init__.py
py4macro/py4macro.py
py4macro/data/bigmac.csv.bz2
py4macro/data/cycle_dates.csv.bz2
py4macro/data/data1.csv
py4macro/data/data2.csv
py4macro/data/data3.csv
py4macro/data/data4.csv
py4macro/data/data5.csv
py4macro/data/debts.csv.bz2
py4macro/data/inequality.csv.bz2
py4macro/data/jpn_annual.csv.bz2
py4macro/data/jpn_money.csv.bz2
py4macro/data/jpn_quarterly.csv.bz2
py4macro/data/mad_country.csv.bz2
py4macro/data/mad_region.csv.bz2
py4macro/data/pwt_data.csv.bz2
py4macro/data/pwt_definitions.csv
py4macro/data/real_ex_rate.csv.bz2
py4macro/data/weo.csv.bz2
py4macro/data/weo_description.csv.bz2
py4macro/data/world_money.csv.bz2
py4macro-0.8.16.dist-info/licenses/LICENSE
py4macro-0.8.16.dist-info/METADATA
py4macro-0.8.16.dist-info/WHEEL
py4macro-0.8.16.dist-info/top_level.txt
py4macro-0.8.16.dist-info/RECORD
