Metadata-Version: 2.4
Name: py4macro
Version: 0.8.16
Summary: A module for py4macro.github.io
Home-page: https://github.com/Py4Macro/py4macro
Author: Tetsu Haruyama
Author-email: haruyama@econ.kobe-u.ac.jp
License: MIT
Keywords: data,Penn World Table,IMF World Economic Outlook,Maddison Project,Hodrick-Prescott filter,Japan
License-File: LICENSE
Requires-Dist: pandas
Dynamic: author
Dynamic: author-email
Dynamic: description
Dynamic: description-content-type
Dynamic: home-page
Dynamic: keywords
Dynamic: license
Dynamic: license-file
Dynamic: requires-dist
Dynamic: summary
